Workbook

Sheet Assumptions
A1: ShiftBuddy — MASTER ASSUMPTIONS (Edit Yellow Cells)
A3: OPERATIONAL PARAMETERS
A4: Messages per operator per day | B4: 4
A5: Working days per month | B5: 22
A6: % Template messages (paid) | B6: 0.5
A7: % Service messages (free 24h window) | B7: 0.5
A8: Escalation rate (no response) | B8: 0.15
A9: Messages/operator/month (calculated) | B9: =B4*B5
A11: GROWTH ASSUMPTIONS
A12: Year 1 — End of Year Operators | B12: 200
A13: Year 2 — Growth Rate | B13: 0.5
A14: Year 3 — Growth Rate | B14: 1
A15: Year 2 — End of Year Operators | B15: =ROUND(B12*(1+B13),0)
A16: Year 3 — End of Year Operators | B16: =ROUND(B15*(1+B14),0)
A17: Year 1 — Avg Monthly Operators | B17: =ROUND(B12/2,0)
A18: Year 2 — Avg Monthly Operators | B18: =ROUND((B12+B15)/2,0)
A19: Year 3 — Avg Monthly Operators | B19: =ROUND((B15+B16)/2,0)
A21: PRICING TIERS (€/month flat)
A22: Starter Tier Price (€/month) | B22: 99
A23: Pro Tier Price (€/month) | B23: 199
A24: Avg operators per customer | B24: 10
A25: % Starter customers | B25: 0.6
A26: % Pro customers | B26: 0.4
A28: WHATSAPP PRICING (Italy/EU) €
A29: Utility template cost (€) | B29: 0.03
A30: Marketing template cost (€) | B30: 0.15
A31: AI-generated message cost (€, from Feb 2026) | B31: 0.057
A32: Service message cost (within 24h) | B32: 0
A34: PROVIDER MARKUPS (€/msg)
A35: Provider | B35: Monthly Fee € | C35: Markup/msg € | D35: Notes
A36: Cloud API Direct | B36: 0 | C36: 0 | D36: Meta direct, no middleman
A37: 360dialog | B37: 49 | C37: 0 | D37: Flat €49 + Meta costs
A38: Twilio | B38: 0 | C38: 0.005 | D38: Pay-as-you-go + markup
A39: Gupshup | B39: 0 | C39: 0.001 | D39: Cheapest markup
A40: WATI | B40: 40 | C40: 0.006 | D40: SMB subscription model
A42: LLM COSTS
A43: Avg input tokens per message | B43: 500
A44: Avg output tokens per message | B44: 300
A45: % messages needing LLM processing | B45: 0.6
A46: Sonnet 4.5 — Input price ($/1M tokens) | B46: 3
A47: Sonnet 4.5 — Output price ($/1M tokens) | B47: 15
A48: Haiku 3.5 — Input price ($/1M tokens) | B48: 0.8
A49: Haiku 3.5 — Output price ($/1M tokens) | B49: 4
A50: USD to EUR exchange rate | B50: 0.92
A51: Sonnet 4.5 cost/message (€) | B51: =(B43*B46/1000000 + B44*B47/1000000)*B50
A52: Haiku 3.5 cost/message (€) | B52: =(B43*B48/1000000 + B44*B49/1000000)*B50
A54: SERVER / INFRASTRUCTURE
A55: Base server cost (€/month) | B55: 30
A56: Additional cost per 100 operators (€/month) | B56: 15
A57: Other SaaS tools (€/month) | B57: 50

Sheet Provider Costs
A1: MONTHLY COST BY PROVIDER & VOLUME
A3: Volume Tier
A4: # Operators | B4: 50 | C4: 100 | D4: 200 | E4: 500 | F4: 1000
A5: Messages/month | B5: =B4*Assumptions!B9 | C5: =C4*Assumptions!B9 | D5: =D4*Assumptions!B9 | E5: =E4*Assumptions!B9 | F5: =F4*Assumptions!B9
A6: Template msgs (paid) | B6: =B5*Assumptions!B6 | C6: =C5*Assumptions!B6 | D6: =D5*Assumptions!B6 | E6: =E5*Assumptions!B6 | F6: =F5*Assumptions!B6
A7: Service msgs (free) | B7: =B5*Assumptions!B7 | C7: =C5*Assumptions!B7 | D7: =D5*Assumptions!B7 | E7: =E5*Assumptions!B7 | F7: =F5*Assumptions!B7
A9: MONTHLY WHATSAPP COST BY PROVIDER (€)
A10: Cloud API Direct | B10: =Assumptions!B36 + B6*(Assumptions!B29 + Assumptions!C36) | C10: =Assumptions!B36 + C6*(Assumptions!B29 + Assumptions!C36) | D10: =Assumptions!B36 + D6*(Assumptions!B29 + Assumptions!C36) | E10: =Assumptions!B36 + E6*(Assumptions!B29 + Assumptions!C36) | F10: =Assumptions!B36 + F6*(Assumptions!B29 + Assumptions!C36)
A11: 360dialog | B11: =Assumptions!B37 + B6*(Assumptions!B29 + Assumptions!C37) | C11: =Assumptions!B37 + C6*(Assumptions!B29 + Assumptions!C37) | D11: =Assumptions!B37 + D6*(Assumptions!B29 + Assumptions!C37) | E11: =Assumptions!B37 + E6*(Assumptions!B29 + Assumptions!C37) | F11: =Assumptions!B37 + F6*(Assumptions!B29 + Assumptions!C37)
A12: Twilio | B12: =Assumptions!B38 + B6*(Assumptions!B29 + Assumptions!C38) | C12: =Assumptions!B38 + C6*(Assumptions!B29 + Assumptions!C38) | D12: =Assumptions!B38 + D6*(Assumptions!B29 + Assumptions!C38) | E12: =Assumptions!B38 + E6*(Assumptions!B29 + Assumptions!C38) | F12: =Assumptions!B38 + F6*(Assumptions!B29 + Assumptions!C38)
A13: Gupshup | B13: =Assumptions!B39 + B6*(Assumptions!B29 + Assumptions!C39) | C13: =Assumptions!B39 + C6*(Assumptions!B29 + Assumptions!C39) | D13: =Assumptions!B39 + D6*(Assumptions!B29 + Assumptions!C39) | E13: =Assumptions!B39 + E6*(Assumptions!B29 + Assumptions!C39) | F13: =Assumptions!B39 + F6*(Assumptions!B29 + Assumptions!C39)
A14: WATI | B14: =Assumptions!B40 + B6*(Assumptions!B29 + Assumptions!C40) | C14: =Assumptions!B40 + C6*(Assumptions!B29 + Assumptions!C40) | D14: =Assumptions!B40 + D6*(Assumptions!B29 + Assumptions!C40) | E14: =Assumptions!B40 + E6*(Assumptions!B29 + Assumptions!C40) | F14: =Assumptions!B40 + F6*(Assumptions!B29 + Assumptions!C40)
A16: CHEAPEST PROVIDER
B17: =INDEX(A10:A14,MATCH(MIN(B10:B14),B10:B14,0)) | C17: =INDEX(A10:A14,MATCH(MIN(C10:C14),C10:C14,0)) | D17: =INDEX(A10:A14,MATCH(MIN(D10:D14),D10:D14,0)) | E17: =INDEX(A10:A14,MATCH(MIN(E10:E14),E10:E14,0)) | F17: =INDEX(A10:A14,MATCH(MIN(F10:F14),F10:F14,0))
A18: Lowest Cost (€) | B18: =MIN(B10:B14) | C18: =MIN(C10:C14) | D18: =MIN(D10:D14) | E18: =MIN(E10:E14) | F18: =MIN(F10:F14)

Sheet LLM Costs
A1: LLM COST ANALYSIS — SONNET 4.5 vs HAIKU 3.5
A3: PER-MESSAGE COSTS
B4: Sonnet 4.5 | C4: Haiku 3.5
A5: Cost per LLM-processed message (€) | B5: =Assumptions!B51 | C5: =Assumptions!B52
A6: % messages needing LLM | B6: =Assumptions!B45 | C6: =Assumptions!B45
A9: MONTHLY LLM COST BY OPERATOR COUNT
A10: # Operators | B10: 50 | C10: 100 | D10: 200 | E10: 500 | F10: 1000
A11: Total messages/month | B11: =B10*Assumptions!B9 | C11: =C10*Assumptions!B9 | D11: =D10*Assumptions!B9 | E11: =E10*Assumptions!B9 | F11: =F10*Assumptions!B9
A12: LLM-processed messages/month | B12: =B11*Assumptions!B45 | C12: =C11*Assumptions!B45 | D12: =D11*Assumptions!B45 | E12: =E11*Assumptions!B45 | F12: =F11*Assumptions!B45
A14: Sonnet 4.5 — Monthly LLM Cost (€) | B14: =B12*Assumptions!B51 | C14: =C12*Assumptions!B51 | D14: =D12*Assumptions!B51 | E14: =E12*Assumptions!B51 | F14: =F12*Assumptions!B51
A15: Haiku 3.5 — Monthly LLM Cost (€) | B15: =B12*Assumptions!B52 | C15: =C12*Assumptions!B52 | D15: =D12*Assumptions!B52 | E15: =E12*Assumptions!B52 | F15: =F12*Assumptions!B52
A17: LLM COST PER OPERATOR / MONTH
A18: Sonnet 4.5 — per operator (€) | B18: =B14/B10 | C18: =C14/C10 | D18: =D14/D10 | E18: =E14/E10 | F18: =F14/F10
A19: Haiku 3.5 — per operator (€) | B19: =B15/B10 | C19: =C15/C10 | D19: =D15/D10 | E19: =E15/E10 | F19: =F15/F10
A21: SAVINGS: SONNET vs HAIKU
A22: Monthly savings with Haiku (€) | B22: =B14-B15 | C22: =C14-C15 | D22: =D14-D15 | E22: =E14-E15 | F22: =F14-F15
A23: Annual savings with Haiku (€) | B23: =B22*12 | C23: =C22*12 | D23: =D22*12 | E23: =E22*12 | F23: =F22*12

Sheet 3-Year Projections
A1: 3-YEAR PROJECTIONS (All Providers × LLM Models)
A3: VOLUME METRICS (from Assumptions)
B4: Year 1 | C4: Year 2 | D4: Year 3
A5: End of Year Operators | B5: =Assumptions!B12 | C5: =Assumptions!B15 | D5: =Assumptions!B16
A6: Avg Monthly Operators | B6: =Assumptions!B17 | C6: =Assumptions!B18 | D6: =Assumptions!B19
A7: Total Customers | B7: =ROUND(B6/Assumptions!B24,0) | C7: =ROUND(C6/Assumptions!B24,0) | D7: =ROUND(D6/Assumptions!B24,0)
A8: Messages/month | B8: =B6*Assumptions!B9 | C8: =C6*Assumptions!B9 | D8: =D6*Assumptions!B9
A9: Template msgs/month (paid) | B9: =B8*Assumptions!B6 | C9: =C8*Assumptions!B6 | D9: =D8*Assumptions!B6
A10: LLM-processed msgs/month | B10: =B8*Assumptions!B45 | C10: =C8*Assumptions!B45 | D10: =D8*Assumptions!B45
A12: REVENUE (€)
A13: Starter Revenue/month | B13: =ROUND(B7*Assumptions!B25,0)*Assumptions!B22 | C13: =ROUND(C7*Assumptions!B25,0)*Assumptions!B22 | D13: =ROUND(D7*Assumptions!B25,0)*Assumptions!B22
A14: Pro Revenue/month | B14: =ROUND(B7*Assumptions!B26,0)*Assumptions!B23 | C14: =ROUND(C7*Assumptions!B26,0)*Assumptions!B23 | D14: =ROUND(D7*Assumptions!B26,0)*Assumptions!B23
A15: Total Monthly Revenue | B15: =B13+B14 | C15: =C13+C14 | D15: =D13+D14
A16: Annual Revenue | B16: =B15*12 | C16: =C15*12 | D16: =D15*12
A18: INFRASTRUCTURE COSTS (€) — Variable
A19: Server cost/month | B19: =Assumptions!B55+ROUNDUP(B6/100,0)*Assumptions!B56 | C19: =Assumptions!B55+ROUNDUP(C6/100,0)*Assumptions!B56 | D19: =Assumptions!B55+ROUNDUP(D6/100,0)*Assumptions!B56
A20: SaaS tools/month | B20: =Assumptions!B57 | C20: =Assumptions!B57 | D20: =Assumptions!B57
A22: LLM COSTS (€) — Monthly
A23: Sonnet 4.5 — LLM cost/month | B23: =B10*Assumptions!B51 | C23: =C10*Assumptions!B51 | D23: =D10*Assumptions!B51
A24: Haiku 3.5 — LLM cost/month | B24: =B10*Assumptions!B52 | C24: =C10*Assumptions!B52 | D24: =D10*Assumptions!B52
A26: ── CLOUD API DIRECT ──
A27: WhatsApp cost/month | B27: =Assumptions!B36+B9*(Assumptions!B29+Assumptions!C36) | C27: =Assumptions!B36+C9*(Assumptions!B29+Assumptions!C36) | D27: =Assumptions!B36+D9*(Assumptions!B29+Assumptions!C36)
A28: Total cost/month (Sonnet 4.5) | B28: =B27+B23+B19+B20 | C28: =C27+C23+C19+C20 | D28: =D27+D23+D19+D20
A29: Total cost/month (Haiku 3.5) | B29: =B27+B24+B19+B20 | C29: =C27+C24+C19+C20 | D29: =D27+D24+D19+D20
A30: Gross Profit/month (Sonnet) | B30: =B15-B28 | C30: =C15-C28 | D30: =D15-D28
A31: Gross Profit/month (Haiku) | B31: =B15-B29 | C31: =C15-C29 | D31: =D15-D29
A32: Gross Margin % (Sonnet) | B32: =B30/B15 | C32: =C30/C15 | D32: =D30/D15
A33: Gross Margin % (Haiku) | B33: =B31/B15 | C33: =C31/C15 | D33: =D31/D15
A34: Annual Gross Profit (Sonnet) | B34: =B30*12 | C34: =C30*12 | D34: =D30*12
A35: Annual Gross Profit (Haiku) | B35: =B31*12 | C35: =C31*12 | D35: =D31*12
A37: ── 360DIALOG ──
A38: WhatsApp cost/month | B38: =Assumptions!B37+B9*(Assumptions!B29+Assumptions!C37) | C38: =Assumptions!B37+C9*(Assumptions!B29+Assumptions!C37) | D38: =Assumptions!B37+D9*(Assumptions!B29+Assumptions!C37)
A39: Total cost/month (Sonnet 4.5) | B39: =B38+B23+B19+B20 | C39: =C38+C23+C19+C20 | D39: =D38+D23+D19+D20
A40: Total cost/month (Haiku 3.5) | B40: =B38+B24+B19+B20 | C40: =C38+C24+C19+C20 | D40: =D38+D24+D19+D20
A41: Gross Profit/month (Sonnet) | B41: =B15-B39 | C41: =C15-C39 | D41: =D15-D39
A42: Gross Profit/month (Haiku) | B42: =B15-B40 | C42: =C15-C40 | D42: =D15-D40
A43: Gross Margin % (Sonnet) | B43: =B41/B15 | C43: =C41/C15 | D43: =D41/D15
A44: Gross Margin % (Haiku) | B44: =B42/B15 | C44: =C42/C15 | D44: =D42/D15
A45: Annual Gross Profit (Sonnet) | B45: =B41*12 | C45: =C41*12 | D45: =D41*12
A46: Annual Gross Profit (Haiku) | B46: =B42*12 | C46: =C42*12 | D46: =D42*12
A48: ── TWILIO ──
A49: WhatsApp cost/month | B49: =Assumptions!B38+B9*(Assumptions!B29+Assumptions!C38) | C49: =Assumptions!B38+C9*(Assumptions!B29+Assumptions!C38) | D49: =Assumptions!B38+D9*(Assumptions!B29+Assumptions!C38)
A50: Total cost/month (Sonnet 4.5) | B50: =B49+B23+B19+B20 | C50: =C49+C23+C19+C20 | D50: =D49+D23+D19+D20
A51: Total cost/month (Haiku 3.5) | B51: =B49+B24+B19+B20 | C51: =C49+C24+C19+C20 | D51: =D49+D24+D19+D20
A52: Gross Profit/month (Sonnet) | B52: =B15-B50 | C52: =C15-C50 | D52: =D15-D50
A53: Gross Profit/month (Haiku) | B53: =B15-B51 | C53: =C15-C51 | D53: =D15-D51
A54: Gross Margin % (Sonnet) | B54: =B52/B15 | C54: =C52/C15 | D54: =D52/D15
A55: Gross Margin % (Haiku) | B55: =B53/B15 | C55: =C53/C15 | D55: =D53/D15
A56: Annual Gross Profit (Sonnet) | B56: =B52*12 | C56: =C52*12 | D56: =D52*12
A57: Annual Gross Profit (Haiku) | B57: =B53*12 | C57: =C53*12 | D57: =D53*12
A59: ── GUPSHUP ──
A60: WhatsApp cost/month | B60: =Assumptions!B39+B9*(Assumptions!B29+Assumptions!C39) | C60: =Assumptions!B39+C9*(Assumptions!B29+Assumptions!C39) | D60: =Assumptions!B39+D9*(Assumptions!B29+Assumptions!C39)
A61: Total cost/month (Sonnet 4.5) | B61: =B60+B23+B19+B20 | C61: =C60+C23+C19+C20 | D61: =D60+D23+D19+D20
A62: Total cost/month (Haiku 3.5) | B62: =B60+B24+B19+B20 | C62: =C60+C24+C19+C20 | D62: =D60+D24+D19+D20
A63: Gross Profit/month (Sonnet) | B63: =B15-B61 | C63: =C15-C61 | D63: =D15-D61
A64: Gross Profit/month (Haiku) | B64: =B15-B62 | C64: =C15-C62 | D64: =D15-D62
A65: Gross Margin % (Sonnet) | B65: =B63/B15 | C65: =C63/C15 | D65: =D63/D15
A66: Gross Margin % (Haiku) | B66: =B64/B15 | C66: =C64/C15 | D66: =D64/D15
A67: Annual Gross Profit (Sonnet) | B67: =B63*12 | C67: =C63*12 | D67: =D63*12
A68: Annual Gross Profit (Haiku) | B68: =B64*12 | C68: =C64*12 | D68: =D64*12
A70: ── WATI ──
A71: WhatsApp cost/month | B71: =Assumptions!B40+B9*(Assumptions!B29+Assumptions!C40) | C71: =Assumptions!B40+C9*(Assumptions!B29+Assumptions!C40) | D71: =Assumptions!B40+D9*(Assumptions!B29+Assumptions!C40)
A72: Total cost/month (Sonnet 4.5) | B72: =B71+B23+B19+B20 | C72: =C71+C23+C19+C20 | D72: =D71+D23+D19+D20
A73: Total cost/month (Haiku 3.5) | B73: =B71+B24+B19+B20 | C73: =C71+C24+C19+C20 | D73: =D71+D24+D19+D20
A74: Gross Profit/month (Sonnet) | B74: =B15-B72 | C74: =C15-C72 | D74: =D15-D72
A75: Gross Profit/month (Haiku) | B75: =B15-B73 | C75: =C15-C73 | D75: =D15-D73
A76: Gross Margin % (Sonnet) | B76: =B74/B15 | C76: =C74/C15 | D76: =D74/D15
A77: Gross Margin % (Haiku) | B77: =B75/B15 | C77: =C75/C15 | D77: =D75/D15
A78: Annual Gross Profit (Sonnet) | B78: =B74*12 | C78: =C74*12 | D78: =D74*12
A79: Annual Gross Profit (Haiku) | B79: =B75*12 | C79: =C75*12 | D79: =D75*12

Sheet Break-Even
A1: BREAK-EVEN ANALYSIS
A3: FIXED COSTS (Monthly)
B4: Sonnet 4.5 | C4: Haiku 3.5
A5: Base server cost | B5: =Assumptions!B55 | C5: =Assumptions!B55
A6: SaaS tools | B6: =Assumptions!B57 | C6: =Assumptions!B57
A7: Total Fixed Costs | B7: =B5+B6 | C7: =C5+C6
A9: VARIABLE COSTS (per operator/month)
A10: WhatsApp Meta cost per operator (Cloud API) | B10: =Assumptions!B29*Assumptions!B9*Assumptions!B6 | C10: =B10
A11: LLM cost per operator/month | B11: =Assumptions!B9*Assumptions!B45*Assumptions!B51 | C11: =Assumptions!B9*Assumptions!B45*Assumptions!B52
A12: Server scaling per operator | B12: =Assumptions!B56/100 | C12: =Assumptions!B56/100
A13: Total Variable Cost per Operator | B13: =B10+B11+B12 | C13: =C10+C11+C12
A15: REVENUE & BREAK-EVEN
A16: Avg Revenue per Operator/month | B16: =(Assumptions!B22*Assumptions!B25+Assumptions!B23*Assumptions!B26)/Assumptions!B24 | C16: =B16
A17: Contribution Margin per Operator | B17: =B16-B13 | C17: =C16-C13
A18: Break-Even # of Operators | B18: =ROUNDUP(B7/B17,0) | C18: =ROUNDUP(C7/C17,0)
A19: Break-Even # of Customers | B19: =ROUNDUP(B18/Assumptions!B24,0) | C19: =ROUNDUP(C18/Assumptions!B24,0)

Sheet Sensitivity
A1: SENSITIVITY — GROSS MARGIN % (Haiku, Cloud API Direct)
A3: Operators → | B3: 50 | C3: 100 | D3: 200 | E3: 500 | F3: 1000
A4: Price/Operator ↓
A5: 5 | B5: =1-((Assumptions!B29*Assumptions!B9*Assumptions!B6+Assumptions!B9*Assumptions!B45*Assumptions!B52+Assumptions!B56/100)*B3+Assumptions!B55+Assumptions!B57)/($A5*B3) | C5: =1-((Assumptions!B29*Assumptions!B9*Assumptions!B6+Assumptions!B9*Assumptions!B45*Assumptions!B52+Assumptions!B56/100)*C3+Assumptions!B55+Assumptions!B57)/($A5*C3) | D5: =1-((Assumptions!B29*Assumptions!B9*Assumptions!B6+Assumptions!B9*Assumptions!B45*Assumptions!B52+Assumptions!B56/100)*D3+Assumptions!B55+Assumptions!B57)/($A5*D3) | E5: =1-((Assumptions!B29*Assumptions!B9*Assumptions!B6+Assumptions!B9*Assumptions!B45*Assumptions!B52+Assumptions!B56/100)*E3+Assumptions!B55+Assumptions!B57)/($A5*E3) | F5: =1-((Assumptions!B29*Assumptions!B9*Assumptions!B6+Assumptions!B9*Assumptions!B45*Assumptions!B52+Assumptions!B56/100)*F3+Assumptions!B55+Assumptions!B57)/($A5*F3)
A6: 8 | B6: =1-((Assumptions!B29*Assumptions!B9*Assumptions!B6+Assumptions!B9*Assumptions!B45*Assumptions!B52+Assumptions!B56/100)*B3+Assumptions!B55+Assumptions!B57)/($A6*B3) | C6: =1-((Assumptions!B29*Assumptions!B9*Assumptions!B6+Assumptions!B9*Assumptions!B45*Assumptions!B52+Assumptions!B56/100)*C3+Assumptions!B55+Assumptions!B57)/($A6*C3) | D6: =1-((Assumptions!B29*Assumptions!B9*Assumptions!B6+Assumptions!B9*Assumptions!B45*Assumptions!B52+Assumptions!B56/100)*D3+Assumptions!B55+Assumptions!B57)/($A6*D3) | E6: =1-((Assumptions!B29*Assumptions!B9*Assumptions!B6+Assumptions!B9*Assumptions!B45*Assumptions!B52+Assumptions!B56/100)*E3+Assumptions!B55+Assumptions!B57)/($A6*E3) | F6: =1-((Assumptions!B29*Assumptions!B9*Assumptions!B6+Assumptions!B9*Assumptions!B45*Assumptions!B52+Assumptions!B56/100)*F3+Assumptions!B55+Assumptions!B57)/($A6*F3)
A7: 10 | B7: =1-((Assumptions!B29*Assumptions!B9*Assumptions!B6+Assumptions!B9*Assumptions!B45*Assumptions!B52+Assumptions!B56/100)*B3+Assumptions!B55+Assumptions!B57)/($A7*B3) | C7: =1-((Assumptions!B29*Assumptions!B9*Assumptions!B6+Assumptions!B9*Assumptions!B45*Assumptions!B52+Assumptions!B56/100)*C3+Assumptions!B55+Assumptions!B57)/($A7*C3) | D7: =1-((Assumptions!B29*Assumptions!B9*Assumptions!B6+Assumptions!B9*Assumptions!B45*Assumptions!B52+Assumptions!B56/100)*D3+Assumptions!B55+Assumptions!B57)/($A7*D3) | E7: =1-((Assumptions!B29*Assumptions!B9*Assumptions!B6+Assumptions!B9*Assumptions!B45*Assumptions!B52+Assumptions!B56/100)*E3+Assumptions!B55+Assumptions!B57)/($A7*E3) | F7: =1-((Assumptions!B29*Assumptions!B9*Assumptions!B6+Assumptions!B9*Assumptions!B45*Assumptions!B52+Assumptions!B56/100)*F3+Assumptions!B55+Assumptions!B57)/($A7*F3)
A8: 12 | B8: =1-((Assumptions!B29*Assumptions!B9*Assumptions!B6+Assumptions!B9*Assumptions!B45*Assumptions!B52+Assumptions!B56/100)*B3+Assumptions!B55+Assumptions!B57)/($A8*B3) | C8: =1-((Assumptions!B29*Assumptions!B9*Assumptions!B6+Assumptions!B9*Assumptions!B45*Assumptions!B52+Assumptions!B56/100)*C3+Assumptions!B55+Assumptions!B57)/($A8*C3) | D8: =1-((Assumptions!B29*Assumptions!B9*Assumptions!B6+Assumptions!B9*Assumptions!B45*Assumptions!B52+Assumptions!B56/100)*D3+Assumptions!B55+Assumptions!B57)/($A8*D3) | E8: =1-((Assumptions!B29*Assumptions!B9*Assumptions!B6+Assumptions!B9*Assumptions!B45*Assumptions!B52+Assumptions!B56/100)*E3+Assumptions!B55+Assumptions!B57)/($A8*E3) | F8: =1-((Assumptions!B29*Assumptions!B9*Assumptions!B6+Assumptions!B9*Assumptions!B45*Assumptions!B52+Assumptions!B56/100)*F3+Assumptions!B55+Assumptions!B57)/($A8*F3)
A9: 15 | B9: =1-((Assumptions!B29*Assumptions!B9*Assumptions!B6+Assumptions!B9*Assumptions!B45*Assumptions!B52+Assumptions!B56/100)*B3+Assumptions!B55+Assumptions!B57)/($A9*B3) | C9: =1-((Assumptions!B29*Assumptions!B9*Assumptions!B6+Assumptions!B9*Assumptions!B45*Assumptions!B52+Assumptions!B56/100)*C3+Assumptions!B55+Assumptions!B57)/($A9*C3) | D9: =1-((Assumptions!B29*Assumptions!B9*Assumptions!B6+Assumptions!B9*Assumptions!B45*Assumptions!B52+Assumptions!B56/100)*D3+Assumptions!B55+Assumptions!B57)/($A9*D3) | E9: =1-((Assumptions!B29*Assumptions!B9*Assumptions!B6+Assumptions!B9*Assumptions!B45*Assumptions!B52+Assumptions!B56/100)*E3+Assumptions!B55+Assumptions!B57)/($A9*E3) | F9: =1-((Assumptions!B29*Assumptions!B9*Assumptions!B6+Assumptions!B9*Assumptions!B45*Assumptions!B52+Assumptions!B56/100)*F3+Assumptions!B55+Assumptions!B57)/($A9*F3)
A10: 20 | B10: =1-((Assumptions!B29*Assumptions!B9*Assumptions!B6+Assumptions!B9*Assumptions!B45*Assumptions!B52+Assumptions!B56/100)*B3+Assumptions!B55+Assumptions!B57)/($A10*B3) | C10: =1-((Assumptions!B29*Assumptions!B9*Assumptions!B6+Assumptions!B9*Assumptions!B45*Assumptions!B52+Assumptions!B56/100)*C3+Assumptions!B55+Assumptions!B57)/($A10*C3) | D10: =1-((Assumptions!B29*Assumptions!B9*Assumptions!B6+Assumptions!B9*Assumptions!B45*Assumptions!B52+Assumptions!B56/100)*D3+Assumptions!B55+Assumptions!B57)/($A10*D3) | E10: =1-((Assumptions!B29*Assumptions!B9*Assumptions!B6+Assumptions!B9*Assumptions!B45*Assumptions!B52+Assumptions!B56/100)*E3+Assumptions!B55+Assumptions!B57)/($A10*E3) | F10: =1-((Assumptions!B29*Assumptions!B9*Assumptions!B6+Assumptions!B9*Assumptions!B45*Assumptions!B52+Assumptions!B56/100)*F3+Assumptions!B55+Assumptions!B57)/($A10*F3)
A12: SENSITIVITY — GROSS MARGIN % (Sonnet 4.5, Cloud API Direct)
A14: Operators → | B14: 50 | C14: 100 | D14: 200 | E14: 500 | F14: 1000
A15: 5 | B15: =1-((Assumptions!B29*Assumptions!B9*Assumptions!B6+Assumptions!B9*Assumptions!B45*Assumptions!B51+Assumptions!B56/100)*B14+Assumptions!B55+Assumptions!B57)/($A15*B14) | C15: =1-((Assumptions!B29*Assumptions!B9*Assumptions!B6+Assumptions!B9*Assumptions!B45*Assumptions!B51+Assumptions!B56/100)*C14+Assumptions!B55+Assumptions!B57)/($A15*C14) | D15: =1-((Assumptions!B29*Assumptions!B9*Assumptions!B6+Assumptions!B9*Assumptions!B45*Assumptions!B51+Assumptions!B56/100)*D14+Assumptions!B55+Assumptions!B57)/($A15*D14) | E15: =1-((Assumptions!B29*Assumptions!B9*Assumptions!B6+Assumptions!B9*Assumptions!B45*Assumptions!B51+Assumptions!B56/100)*E14+Assumptions!B55+Assumptions!B57)/($A15*E14) | F15: =1-((Assumptions!B29*Assumptions!B9*Assumptions!B6+Assumptions!B9*Assumptions!B45*Assumptions!B51+Assumptions!B56/100)*F14+Assumptions!B55+Assumptions!B57)/($A15*F14)
A16: 8 | B16: =1-((Assumptions!B29*Assumptions!B9*Assumptions!B6+Assumptions!B9*Assumptions!B45*Assumptions!B51+Assumptions!B56/100)*B14+Assumptions!B55+Assumptions!B57)/($A16*B14) | C16: =1-((Assumptions!B29*Assumptions!B9*Assumptions!B6+Assumptions!B9*Assumptions!B45*Assumptions!B51+Assumptions!B56/100)*C14+Assumptions!B55+Assumptions!B57)/($A16*C14) | D16: =1-((Assumptions!B29*Assumptions!B9*Assumptions!B6+Assumptions!B9*Assumptions!B45*Assumptions!B51+Assumptions!B56/100)*D14+Assumptions!B55+Assumptions!B57)/($A16*D14) | E16: =1-((Assumptions!B29*Assumptions!B9*Assumptions!B6+Assumptions!B9*Assumptions!B45*Assumptions!B51+Assumptions!B56/100)*E14+Assumptions!B55+Assumptions!B57)/($A16*E14) | F16: =1-((Assumptions!B29*Assumptions!B9*Assumptions!B6+Assumptions!B9*Assumptions!B45*Assumptions!B51+Assumptions!B56/100)*F14+Assumptions!B55+Assumptions!B57)/($A16*F14)
A17: 10 | B17: =1-((Assumptions!B29*Assumptions!B9*Assumptions!B6+Assumptions!B9*Assumptions!B45*Assumptions!B51+Assumptions!B56/100)*B14+Assumptions!B55+Assumptions!B57)/($A17*B14) | C17: =1-((Assumptions!B29*Assumptions!B9*Assumptions!B6+Assumptions!B9*Assumptions!B45*Assumptions!B51+Assumptions!B56/100)*C14+Assumptions!B55+Assumptions!B57)/($A17*C14) | D17: =1-((Assumptions!B29*Assumptions!B9*Assumptions!B6+Assumptions!B9*Assumptions!B45*Assumptions!B51+Assumptions!B56/100)*D14+Assumptions!B55+Assumptions!B57)/($A17*D14) | E17: =1-((Assumptions!B29*Assumptions!B9*Assumptions!B6+Assumptions!B9*Assumptions!B45*Assumptions!B51+Assumptions!B56/100)*E14+Assumptions!B55+Assumptions!B57)/($A17*E14) | F17: =1-((Assumptions!B29*Assumptions!B9*Assumptions!B6+Assumptions!B9*Assumptions!B45*Assumptions!B51+Assumptions!B56/100)*F14+Assumptions!B55+Assumptions!B57)/($A17*F14)
A18: 12 | B18: =1-((Assumptions!B29*Assumptions!B9*Assumptions!B6+Assumptions!B9*Assumptions!B45*Assumptions!B51+Assumptions!B56/100)*B14+Assumptions!B55+Assumptions!B57)/($A18*B14) | C18: =1-((Assumptions!B29*Assumptions!B9*Assumptions!B6+Assumptions!B9*Assumptions!B45*Assumptions!B51+Assumptions!B56/100)*C14+Assumptions!B55+Assumptions!B57)/($A18*C14) | D18: =1-((Assumptions!B29*Assumptions!B9*Assumptions!B6+Assumptions!B9*Assumptions!B45*Assumptions!B51+Assumptions!B56/100)*D14+Assumptions!B55+Assumptions!B57)/($A18*D14) | E18: =1-((Assumptions!B29*Assumptions!B9*Assumptions!B6+Assumptions!B9*Assumptions!B45*Assumptions!B51+Assumptions!B56/100)*E14+Assumptions!B55+Assumptions!B57)/($A18*E14) | F18: =1-((Assumptions!B29*Assumptions!B9*Assumptions!B6+Assumptions!B9*Assumptions!B45*Assumptions!B51+Assumptions!B56/100)*F14+Assumptions!B55+Assumptions!B57)/($A18*F14)
A19: 15 | B19: =1-((Assumptions!B29*Assumptions!B9*Assumptions!B6+Assumptions!B9*Assumptions!B45*Assumptions!B51+Assumptions!B56/100)*B14+Assumptions!B55+Assumptions!B57)/($A19*B14) | C19: =1-((Assumptions!B29*Assumptions!B9*Assumptions!B6+Assumptions!B9*Assumptions!B45*Assumptions!B51+Assumptions!B56/100)*C14+Assumptions!B55+Assumptions!B57)/($A19*C14) | D19: =1-((Assumptions!B29*Assumptions!B9*Assumptions!B6+Assumptions!B9*Assumptions!B45*Assumptions!B51+Assumptions!B56/100)*D14+Assumptions!B55+Assumptions!B57)/($A19*D14) | E19: =1-((Assumptions!B29*Assumptions!B9*Assumptions!B6+Assumptions!B9*Assumptions!B45*Assumptions!B51+Assumptions!B56/100)*E14+Assumptions!B55+Assumptions!B57)/($A19*E14) | F19: =1-((Assumptions!B29*Assumptions!B9*Assumptions!B6+Assumptions!B9*Assumptions!B45*Assumptions!B51+Assumptions!B56/100)*F14+Assumptions!B55+Assumptions!B57)/($A19*F14)
A20: 20 | B20: =1-((Assumptions!B29*Assumptions!B9*Assumptions!B6+Assumptions!B9*Assumptions!B45*Assumptions!B51+Assumptions!B56/100)*B14+Assumptions!B55+Assumptions!B57)/($A20*B14) | C20: =1-((Assumptions!B29*Assumptions!B9*Assumptions!B6+Assumptions!B9*Assumptions!B45*Assumptions!B51+Assumptions!B56/100)*C14+Assumptions!B55+Assumptions!B57)/($A20*C14) | D20: =1-((Assumptions!B29*Assumptions!B9*Assumptions!B6+Assumptions!B9*Assumptions!B45*Assumptions!B51+Assumptions!B56/100)*D14+Assumptions!B55+Assumptions!B57)/($A20*D14) | E20: =1-((Assumptions!B29*Assumptions!B9*Assumptions!B6+Assumptions!B9*Assumptions!B45*Assumptions!B51+Assumptions!B56/100)*E14+Assumptions!B55+Assumptions!B57)/($A20*E14) | F20: =1-((Assumptions!B29*Assumptions!B9*Assumptions!B6+Assumptions!B9*Assumptions!B45*Assumptions!B51+Assumptions!B56/100)*F14+Assumptions!B55+Assumptions!B57)/($A20*F14)
